{
	"nile" : "Egypt",
	"amstel" : "Netherlands",
	"tigris" : "Iraq",
	"chao phraya" : "gujarat",
	"ghoomar" : "Thailand",
	"danube" : "Yugoslavia",
	"spree" : "Germany",
	"bogotá" : "Colombia",
	"senne" : "Belgium",
	"danube, sava" : "Hungary",
	"río de la plata" : "Argentina",
	"hugli" : "India",
	"barada" : "Syria",
	"yamuna" : "India",
	"lIffey" : "Ireland",
	"saigon" : "Vietnam",
	"pearl" : "China",
	"liwung" : "Indonesia",
	"dnieper" : "Ukraine",
	"tagus" : "Portugal",
	"rímac" : "Peru",
	"thames" : "England",
	"manzanares" : "Spain",
	"yarra" : "Australia",
	"st. lawrence" : "Canada",
	"moskva" : "Russia",
	"seine" : "France",
	"moldau": "Czech Republic",
	"tiber" : "Italy",
	"neva" : "Russia",
	"mapocho" : "Chile",
	"tietê" : "Brazil",
	"han" : "South Korea",
	"huangpu" : "China",
	"sumida" : "Japan",
	"vistula" : "Poland",
	"sava" : "Croatia",
	"limmat" : "Switzerland"

}